<annotation>
  <folder>VOC2007</folder>
  <filename>3846.jpg</filename>
  <source>
    <database>Coco database</database>
  </source>
  <size>
    <width>2304</width>
    <height>1296</height>
    <depth>3</depth>
  </size>
  <segmented>0</segmented>
  <object>
    <name>belt</name>
    <pose>Unspecified</pose>
    <truncated>0</truncated>
    <difficult>0</difficult>
    <bndbox>
      <xmin>973</xmin>
      <ymin>138</ymin>
      <xmax>1370</xmax>
      <ymax>1132</ymax>
    </bndbox>
  </object>
  <object>
    <name>bag</name>
    <pose>Unspecified</pose>
    <truncated>0</truncated>
    <difficult>0</difficult>
    <bndbox>
      <xmin>1103</xmin>
      <ymin>648</ymin>
      <xmax>1266</xmax>
      <ymax>882</ymax>
    </bndbox>
  </object>
  <object>
    <name>bag</name>
    <pose>Unspecified</pose>
    <truncated>0</truncated>
    <difficult>0</difficult>
    <bndbox>
      <xmin>1088</xmin>
      <ymin>57</ymin>
      <xmax>1215</xmax>
      <ymax>212</ymax>
    </bndbox>
  </object>
</annotation>
